trbinance/__init__.py
trbinance/async_client.py
trbinance/baseclient.py
trbinance/client.py
trbinance/defines.py
trbinance/helper.py
trbinance-0.1.2.dist-info/METADATA
trbinance-0.1.2.dist-info/WHEEL
trbinance-0.1.2.dist-info/top_level.txt
trbinance-0.1.2.dist-info/RECORD
