Metadata-Version: 2.1
Name: trbinance
Version: 0.1.2
Summary: Trbinance wrapper
Home-page: https://github.com/yourusername/trbinance
Author: Akasimo
Author-email: akasimo@fastmail.com
